hologen/__init__.py
hologen/converters.py
hologen/shapes.py
hologen/types.py
hologen/holography/inline.py
hologen/holography/off_axis.py
hologen/holography/propagation.py
hologen/utils/io.py
hologen/utils/math.py
hologen-0.1.0.dist-info/licenses/LICENSE
hologen-0.1.0.dist-info/METADATA
hologen-0.1.0.dist-info/WHEEL
hologen-0.1.0.dist-info/top_level.txt
hologen-0.1.0.dist-info/RECORD
