Metadata-Version: 2.4
Name: hologen
Version: 0.1.0
Summary: Holography dataset generation toolkit
Author-email: Gyokhan Kochmarla <hello@gyokhan.com>
License: MIT
Requires-Python: >=3.13
License-File: LICENSE
Requires-Dist: numpy<2.4,>=2.3
Requires-Dist: pillow<13.0,>=12.0
Provides-Extra: dev
Requires-Dist: black>=24.0; extra == "dev"
Requires-Dist: ruff>=0.2; extra == "dev"
Requires-Dist: pytest>=8.0; extra == "dev"
Requires-Dist: pytest-cov>=4.0; extra == "dev"
Dynamic: license-file
